{
  "id": "linux/service-check-commands",
  "title": "Service Check Commands for CentOS",
  "description": "Overview",
  "source": "@site/docs/linux/service-check-commands.md",
  "sourceDirName": "linux",
  "slug": "/linux/service-check-commands",
  "permalink": "/docs/linux/service-check-commands",
  "draft": false,
  "unlisted": false,
  "editUrl": "https://github.com/facebook/docusaurus/tree/main/packages/create-docusaurus/templates/shared/docs/linux/service-check-commands.md",
  "tags": [],
  "version": "current",
  "frontMatter": {},
  "sidebar": "tutorialSidebar",
  "previous": {
    "title": "One-Line Bash Commands",
    "permalink": "/docs/linux/oneline-commands"
  }
}